<annotation>
	<folder></folder>
	<filename>coolermaster2_jpg.rf.74e057b8f1831e1910a395be310df88e.jpg</filename>
	<path>coolermaster2_jpg.rf.74e057b8f1831e1910a395be310df88e.jpg</path>
	<source>
		<database>roboflow.ai</database>
	</source>
	<size>
		<width>1580</width>
		<height>1580</height>
		<depth>3</depth>
	</size>
	<segmented>0</segmented>
	<object>
		<name>tab</name>
		<pose>Unspecified</pose>
		<truncated>0</truncated>
		<difficult>0</difficult>
		<occluded>0</occluded>
		<bndbox>
			<xmin>25</xmin>
			<xmax>156</xmax>
			<ymin>629</ymin>
			<ymax>724</ymax>
		</bndbox>
	</object>
	<object>
		<name>9</name>
		<pose>Unspecified</pose>
		<truncated>0</truncated>
		<difficult>0</difficult>
		<occluded>0</occluded>
		<bndbox>
			<xmin>952</xmin>
			<xmax>1035</xmax>
			<ymin>522</ymin>
			<ymax>619</ymax>
		</bndbox>
	</object>
	<object>
		<name>keyboard</name>
		<pose>Unspecified</pose>
		<truncated>0</truncated>
		<difficult>0</difficult>
		<occluded>0</occluded>
		<bndbox>
			<xmin>1</xmin>
			<xmax>1575</xmax>
			<ymin>499</ymin>
			<ymax>1074</ymax>
		</bndbox>
	</object>
	<object>
		<name>0</name>
		<pose>Unspecified</pose>
		<truncated>0</truncated>
		<difficult>0</difficult>
		<occluded>0</occluded>
		<bndbox>
			<xmin>1054</xmin>
			<xmax>1139</xmax>
			<ymin>521</ymin>
			<ymax>620</ymax>
		</bndbox>
	</object>
	<object>
		<name>l</name>
		<pose>Unspecified</pose>
		<truncated>0</truncated>
		<difficult>0</difficult>
		<occluded>0</occluded>
		<bndbox>
			<xmin>1032</xmin>
			<xmax>1109</xmax>
			<ymin>735</ymin>
			<ymax>830</ymax>
		</bndbox>
	</object>
	<object>
		<name>j</name>
		<pose>Unspecified</pose>
		<truncated>0</truncated>
		<difficult>0</difficult>
		<occluded>0</occluded>
		<bndbox>
			<xmin>827</xmin>
			<xmax>904</xmax>
			<ymin>731</ymin>
			<ymax>826</ymax>
		</bndbox>
	</object>
	<object>
		<name>4</name>
		<pose>Unspecified</pose>
		<truncated>0</truncated>
		<difficult>0</difficult>
		<occluded>0</occluded>
		<bndbox>
			<xmin>439</xmin>
			<xmax>525</xmax>
			<ymin>525</ymin>
			<ymax>624</ymax>
		</bndbox>
	</object>
	<object>
		<name>i</name>
		<pose>Unspecified</pose>
		<truncated>0</truncated>
		<difficult>0</difficult>
		<occluded>0</occluded>
		<bndbox>
			<xmin>902</xmin>
			<xmax>984</xmax>
			<ymin>630</ymin>
			<ymax>728</ymax>
		</bndbox>
	</object>
	<object>
		<name>e</name>
		<pose>Unspecified</pose>
		<truncated>0</truncated>
		<difficult>0</difficult>
		<occluded>0</occluded>
		<bndbox>
			<xmin>389</xmin>
			<xmax>469</xmax>
			<ymin>628</ymin>
			<ymax>721</ymax>
		</bndbox>
	</object>
	<object>
		<name>space</name>
		<pose>Unspecified</pose>
		<truncated>0</truncated>
		<difficult>0</difficult>
		<occluded>0</occluded>
		<bndbox>
			<xmin>411</xmin>
			<xmax>1041</xmax>
			<ymin>946</ymin>
			<ymax>1045</ymax>
		</bndbox>
	</object>
	<object>
		<name>hash</name>
		<pose>Unspecified</pose>
		<truncated>0</truncated>
		<difficult>0</difficult>
		<occluded>0</occluded>
		<bndbox>
			<xmin>1341</xmin>
			<xmax>1419</xmax>
			<ymin>736</ymin>
			<ymax>831</ymax>
		</bndbox>
	</object>
	<object>
		<name>b</name>
		<pose>Unspecified</pose>
		<truncated>0</truncated>
		<difficult>0</difficult>
		<occluded>0</occluded>
		<bndbox>
			<xmin>647</xmin>
			<xmax>724</xmax>
			<ymin>838</ymin>
			<ymax>934</ymax>
		</bndbox>
	</object>
	<object>
		<name>strg-left</name>
		<pose>Unspecified</pose>
		<truncated>0</truncated>
		<difficult>0</difficult>
		<occluded>0</occluded>
		<bndbox>
			<xmin>23</xmin>
			<xmax>131</xmax>
			<ymin>949</ymin>
			<ymax>1044</ymax>
		</bndbox>
	</object>
	<object>
		<name>6</name>
		<pose>Unspecified</pose>
		<truncated>0</truncated>
		<difficult>0</difficult>
		<occluded>0</occluded>
		<bndbox>
			<xmin>644</xmin>
			<xmax>729</xmax>
			<ymin>521</ymin>
			<ymax>618</ymax>
		</bndbox>
	</object>
	<object>
		<name>q</name>
		<pose>Unspecified</pose>
		<truncated>0</truncated>
		<difficult>0</difficult>
		<occluded>0</occluded>
		<bndbox>
			<xmin>179</xmin>
			<xmax>262</xmax>
			<ymin>628</ymin>
			<ymax>723</ymax>
		</bndbox>
	</object>
	<object>
		<name>shift-lock</name>
		<pose>Unspecified</pose>
		<truncated>0</truncated>
		<difficult>0</difficult>
		<occluded>0</occluded>
		<bndbox>
			<xmin>25</xmin>
			<xmax>187</xmax>
			<ymin>734</ymin>
			<ymax>831</ymax>
		</bndbox>
	</object>
	<object>
		<name>m</name>
		<pose>Unspecified</pose>
		<truncated>0</truncated>
		<difficult>0</difficult>
		<occluded>0</occluded>
		<bndbox>
			<xmin>851</xmin>
			<xmax>931</xmax>
			<ymin>837</ymin>
			<ymax>933</ymax>
		</bndbox>
	</object>
	<object>
		<name>del</name>
		<pose>Unspecified</pose>
		<truncated>0</truncated>
		<difficult>0</difficult>
		<occluded>0</occluded>
		<bndbox>
			<xmin>1363</xmin>
			<xmax>1549</xmax>
			<ymin>524</ymin>
			<ymax>618</ymax>
		</bndbox>
	</object>
	<object>
		<name>p</name>
		<pose>Unspecified</pose>
		<truncated>0</truncated>
		<difficult>0</difficult>
		<occluded>0</occluded>
		<bndbox>
			<xmin>1108</xmin>
			<xmax>1190</xmax>
			<ymin>625</ymin>
			<ymax>723</ymax>
		</bndbox>
	</object>
	<object>
		<name>alt-left</name>
		<pose>Unspecified</pose>
		<truncated>0</truncated>
		<difficult>0</difficult>
		<occluded>0</occluded>
		<bndbox>
			<xmin>281</xmin>
			<xmax>393</xmax>
			<ymin>946</ymin>
			<ymax>1043</ymax>
		</bndbox>
	</object>
	<object>
		<name>x</name>
		<pose>Unspecified</pose>
		<truncated>0</truncated>
		<difficult>0</difficult>
		<occluded>0</occluded>
		<bndbox>
			<xmin>338</xmin>
			<xmax>418</xmax>
			<ymin>838</ymin>
			<ymax>935</ymax>
		</bndbox>
	</object>
	<object>
		<name>z</name>
		<pose>Unspecified</pose>
		<truncated>0</truncated>
		<difficult>0</difficult>
		<occluded>0</occluded>
		<bndbox>
			<xmin>698</xmin>
			<xmax>776</xmax>
			<ymin>626</ymin>
			<ymax>720</ymax>
		</bndbox>
	</object>
	<object>
		<name>n</name>
		<pose>Unspecified</pose>
		<truncated>0</truncated>
		<difficult>0</difficult>
		<occluded>0</occluded>
		<bndbox>
			<xmin>749</xmin>
			<xmax>831</xmax>
			<ymin>837</ymin>
			<ymax>934</ymax>
		</bndbox>
	</object>
	<object>
		<name>comma</name>
		<pose>Unspecified</pose>
		<truncated>0</truncated>
		<difficult>0</difficult>
		<occluded>0</occluded>
		<bndbox>
			<xmin>953</xmin>
			<xmax>1031</xmax>
			<ymin>837</ymin>
			<ymax>934</ymax>
		</bndbox>
	</object>
	<object>
		<name>g</name>
		<pose>Unspecified</pose>
		<truncated>0</truncated>
		<difficult>0</difficult>
		<occluded>0</occluded>
		<bndbox>
			<xmin>622</xmin>
			<xmax>701</xmax>
			<ymin>731</ymin>
			<ymax>828</ymax>
		</bndbox>
	</object>
	<object>
		<name>y</name>
		<pose>Unspecified</pose>
		<truncated>0</truncated>
		<difficult>0</difficult>
		<occluded>0</occluded>
		<bndbox>
			<xmin>234</xmin>
			<xmax>313</xmax>
			<ymin>838</ymin>
			<ymax>935</ymax>
		</bndbox>
	</object>
	<object>
		<name>shift-left</name>
		<pose>Unspecified</pose>
		<truncated>0</truncated>
		<difficult>0</difficult>
		<occluded>0</occluded>
		<bndbox>
			<xmin>22</xmin>
			<xmax>106</xmax>
			<ymin>841</ymin>
			<ymax>937</ymax>
		</bndbox>
	</object>
	<object>
		<name>o</name>
		<pose>Unspecified</pose>
		<truncated>0</truncated>
		<difficult>0</difficult>
		<occluded>0</occluded>
		<bndbox>
			<xmin>1005</xmin>
			<xmax>1087</xmax>
			<ymin>631</ymin>
			<ymax>729</ymax>
		</bndbox>
	</object>
	<object>
		<name>u</name>
		<pose>Unspecified</pose>
		<truncated>0</truncated>
		<difficult>0</difficult>
		<occluded>0</occluded>
		<bndbox>
			<xmin>801</xmin>
			<xmax>883</xmax>
			<ymin>631</ymin>
			<ymax>729</ymax>
		</bndbox>
	</object>
	<object>
		<name>shift-right</name>
		<pose>Unspecified</pose>
		<truncated>0</truncated>
		<difficult>0</difficult>
		<occluded>0</occluded>
		<bndbox>
			<xmin>1264</xmin>
			<xmax>1342</xmax>
			<ymin>842</ymin>
			<ymax>937</ymax>
		</bndbox>
	</object>
	<object>
		<name>ae</name>
		<pose>Unspecified</pose>
		<truncated>0</truncated>
		<difficult>0</difficult>
		<occluded>0</occluded>
		<bndbox>
			<xmin>1240</xmin>
			<xmax>1318</xmax>
			<ymin>736</ymin>
			<ymax>831</ymax>
		</bndbox>
	</object>
	<object>
		<name>altgr-right</name>
		<pose>Unspecified</pose>
		<truncated>0</truncated>
		<difficult>0</difficult>
		<occluded>0</occluded>
		<bndbox>
			<xmin>1058</xmin>
			<xmax>1136</xmax>
			<ymin>947</ymin>
			<ymax>1042</ymax>
		</bndbox>
	</object>
	<object>
		<name>5</name>
		<pose>Unspecified</pose>
		<truncated>0</truncated>
		<difficult>0</difficult>
		<occluded>0</occluded>
		<bndbox>
			<xmin>540</xmin>
			<xmax>626</xmax>
			<ymin>521</ymin>
			<ymax>620</ymax>
		</bndbox>
	</object>
	<object>
		<name>oe</name>
		<pose>Unspecified</pose>
		<truncated>0</truncated>
		<difficult>0</difficult>
		<occluded>0</occluded>
		<bndbox>
			<xmin>1133</xmin>
			<xmax>1215</xmax>
			<ymin>736</ymin>
			<ymax>831</ymax>
		</bndbox>
	</object>
	<object>
		<name>7</name>
		<pose>Unspecified</pose>
		<truncated>0</truncated>
		<difficult>0</difficult>
		<occluded>0</occluded>
		<bndbox>
			<xmin>749</xmin>
			<xmax>829</xmax>
			<ymin>523</ymin>
			<ymax>618</ymax>
		</bndbox>
	</object>
	<object>
		<name>h</name>
		<pose>Unspecified</pose>
		<truncated>0</truncated>
		<difficult>0</difficult>
		<occluded>0</occluded>
		<bndbox>
			<xmin>724</xmin>
			<xmax>803</xmax>
			<ymin>733</ymin>
			<ymax>829</ymax>
		</bndbox>
	</object>
	<object>
		<name>k</name>
		<pose>Unspecified</pose>
		<truncated>0</truncated>
		<difficult>0</difficult>
		<occluded>0</occluded>
		<bndbox>
			<xmin>931</xmin>
			<xmax>1008</xmax>
			<ymin>735</ymin>
			<ymax>830</ymax>
		</bndbox>
	</object>
	<object>
		<name>enter</name>
		<pose>Unspecified</pose>
		<truncated>0</truncated>
		<difficult>0</difficult>
		<occluded>0</occluded>
		<bndbox>
			<xmin>1415</xmin>
			<xmax>1548</xmax>
			<ymin>632</ymin>
			<ymax>830</ymax>
		</bndbox>
	</object>
	<object>
		<name>s</name>
		<pose>Unspecified</pose>
		<truncated>0</truncated>
		<difficult>0</difficult>
		<occluded>0</occluded>
		<bndbox>
			<xmin>312</xmin>
			<xmax>392</xmax>
			<ymin>732</ymin>
			<ymax>828</ymax>
		</bndbox>
	</object>
	<object>
		<name>8</name>
		<pose>Unspecified</pose>
		<truncated>0</truncated>
		<difficult>0</difficult>
		<occluded>0</occluded>
		<bndbox>
			<xmin>850</xmin>
			<xmax>934</xmax>
			<ymin>521</ymin>
			<ymax>620</ymax>
		</bndbox>
	</object>
	<object>
		<name>1</name>
		<pose>Unspecified</pose>
		<truncated>0</truncated>
		<difficult>0</difficult>
		<occluded>0</occluded>
		<bndbox>
			<xmin>127</xmin>
			<xmax>211</xmax>
			<ymin>523</ymin>
			<ymax>620</ymax>
		</bndbox>
	</object>
	<object>
		<name>w</name>
		<pose>Unspecified</pose>
		<truncated>0</truncated>
		<difficult>0</difficult>
		<occluded>0</occluded>
		<bndbox>
			<xmin>286</xmin>
			<xmax>367</xmax>
			<ymin>627</ymin>
			<ymax>722</ymax>
		</bndbox>
	</object>
	<object>
		<name>f</name>
		<pose>Unspecified</pose>
		<truncated>0</truncated>
		<difficult>0</difficult>
		<occluded>0</occluded>
		<bndbox>
			<xmin>520</xmin>
			<xmax>597</xmax>
			<ymin>732</ymin>
			<ymax>826</ymax>
		</bndbox>
	</object>
	<object>
		<name>plus</name>
		<pose>Unspecified</pose>
		<truncated>0</truncated>
		<difficult>0</difficult>
		<occluded>0</occluded>
		<bndbox>
			<xmin>1312</xmin>
			<xmax>1394</xmax>
			<ymin>629</ymin>
			<ymax>727</ymax>
		</bndbox>
	</object>
	<object>
		<name>accent</name>
		<pose>Unspecified</pose>
		<truncated>0</truncated>
		<difficult>0</difficult>
		<occluded>0</occluded>
		<bndbox>
			<xmin>1260</xmin>
			<xmax>1343</xmax>
			<ymin>521</ymin>
			<ymax>620</ymax>
		</bndbox>
	</object>
	<object>
		<name>ss</name>
		<pose>Unspecified</pose>
		<truncated>0</truncated>
		<difficult>0</difficult>
		<occluded>0</occluded>
		<bndbox>
			<xmin>1157</xmin>
			<xmax>1239</xmax>
			<ymin>522</ymin>
			<ymax>619</ymax>
		</bndbox>
	</object>
	<object>
		<name>v</name>
		<pose>Unspecified</pose>
		<truncated>0</truncated>
		<difficult>0</difficult>
		<occluded>0</occluded>
		<bndbox>
			<xmin>542</xmin>
			<xmax>624</xmax>
			<ymin>837</ymin>
			<ymax>933</ymax>
		</bndbox>
	</object>
	<object>
		<name>a</name>
		<pose>Unspecified</pose>
		<truncated>0</truncated>
		<difficult>0</difficult>
		<occluded>0</occluded>
		<bndbox>
			<xmin>210</xmin>
			<xmax>290</xmax>
			<ymin>738</ymin>
			<ymax>834</ymax>
		</bndbox>
	</object>
	<object>
		<name>minus</name>
		<pose>Unspecified</pose>
		<truncated>0</truncated>
		<difficult>0</difficult>
		<occluded>0</occluded>
		<bndbox>
			<xmin>1160</xmin>
			<xmax>1238</xmax>
			<ymin>841</ymin>
			<ymax>936</ymax>
		</bndbox>
	</object>
	<object>
		<name>3</name>
		<pose>Unspecified</pose>
		<truncated>0</truncated>
		<difficult>0</difficult>
		<occluded>0</occluded>
		<bndbox>
			<xmin>333</xmin>
			<xmax>421</xmax>
			<ymin>520</ymin>
			<ymax>621</ymax>
		</bndbox>
	</object>
	<object>
		<name>2</name>
		<pose>Unspecified</pose>
		<truncated>0</truncated>
		<difficult>0</difficult>
		<occluded>0</occluded>
		<bndbox>
			<xmin>230</xmin>
			<xmax>318</xmax>
			<ymin>521</ymin>
			<ymax>620</ymax>
		</bndbox>
	</object>
	<object>
		<name>less</name>
		<pose>Unspecified</pose>
		<truncated>0</truncated>
		<difficult>0</difficult>
		<occluded>0</occluded>
		<bndbox>
			<xmin>129</xmin>
			<xmax>210</xmax>
			<ymin>839</ymin>
			<ymax>936</ymax>
		</bndbox>
	</object>
	<object>
		<name>t</name>
		<pose>Unspecified</pose>
		<truncated>0</truncated>
		<difficult>0</difficult>
		<occluded>0</occluded>
		<bndbox>
			<xmin>596</xmin>
			<xmax>672</xmax>
			<ymin>628</ymin>
			<ymax>720</ymax>
		</bndbox>
	</object>
	<object>
		<name>ue</name>
		<pose>Unspecified</pose>
		<truncated>0</truncated>
		<difficult>0</difficult>
		<occluded>0</occluded>
		<bndbox>
			<xmin>1211</xmin>
			<xmax>1293</xmax>
			<ymin>629</ymin>
			<ymax>727</ymax>
		</bndbox>
	</object>
	<object>
		<name>d</name>
		<pose>Unspecified</pose>
		<truncated>0</truncated>
		<difficult>0</difficult>
		<occluded>0</occluded>
		<bndbox>
			<xmin>417</xmin>
			<xmax>495</xmax>
			<ymin>731</ymin>
			<ymax>827</ymax>
		</bndbox>
	</object>
	<object>
		<name>point</name>
		<pose>Unspecified</pose>
		<truncated>0</truncated>
		<difficult>0</difficult>
		<occluded>0</occluded>
		<bndbox>
			<xmin>1057</xmin>
			<xmax>1135</xmax>
			<ymin>837</ymin>
			<ymax>932</ymax>
		</bndbox>
	</object>
	<object>
		<name>c</name>
		<pose>Unspecified</pose>
		<truncated>0</truncated>
		<difficult>0</difficult>
		<occluded>0</occluded>
		<bndbox>
			<xmin>442</xmin>
			<xmax>520</xmax>
			<ymin>839</ymin>
			<ymax>934</ymax>
		</bndbox>
	</object>
	<object>
		<name>r</name>
		<pose>Unspecified</pose>
		<truncated>0</truncated>
		<difficult>0</difficult>
		<occluded>0</occluded>
		<bndbox>
			<xmin>493</xmin>
			<xmax>572</xmax>
			<ymin>628</ymin>
			<ymax>720</ymax>
		</bndbox>
	</object>
	<object>
		<name>caret</name>
		<pose>Unspecified</pose>
		<truncated>0</truncated>
		<difficult>0</difficult>
		<occluded>0</occluded>
		<bndbox>
			<xmin>21</xmin>
			<xmax>104</xmax>
			<ymin>524</ymin>
			<ymax>620</ymax>
		</bndbox>
	</object>
</annotation>
