<annotation>
	<folder></folder>
	<filename>isy5_jpg.rf.22e78f648f3adde18a0c6ab0cd4756af.jpg</filename>
	<path>isy5_jpg.rf.22e78f648f3adde18a0c6ab0cd4756af.jpg</path>
	<source>
		<database>roboflow.ai</database>
	</source>
	<size>
		<width>954</width>
		<height>716</height>
		<depth>3</depth>
	</size>
	<segmented>0</segmented>
	<object>
		<name>x</name>
		<pose>Unspecified</pose>
		<truncated>0</truncated>
		<difficult>0</difficult>
		<occluded>0</occluded>
		<bndbox>
			<xmin>237</xmin>
			<xmax>269</xmax>
			<ymin>371</ymin>
			<ymax>404</ymax>
		</bndbox>
	</object>
	<object>
		<name>7</name>
		<pose>Unspecified</pose>
		<truncated>0</truncated>
		<difficult>0</difficult>
		<occluded>0</occluded>
		<bndbox>
			<xmin>374</xmin>
			<xmax>406</xmax>
			<ymin>259</ymin>
			<ymax>293</ymax>
		</bndbox>
	</object>
	<object>
		<name>keyboard</name>
		<pose>Unspecified</pose>
		<truncated>0</truncated>
		<difficult>0</difficult>
		<occluded>0</occluded>
		<bndbox>
			<xmin>102</xmin>
			<xmax>955</xmax>
			<ymin>152</ymin>
			<ymax>465</ymax>
		</bndbox>
	</object>
	<object>
		<name>enter</name>
		<pose>Unspecified</pose>
		<truncated>0</truncated>
		<difficult>0</difficult>
		<occluded>0</occluded>
		<bndbox>
			<xmin>611</xmin>
			<xmax>662</xmax>
			<ymin>290</ymin>
			<ymax>360</ymax>
		</bndbox>
	</object>
	<object>
		<name>k</name>
		<pose>Unspecified</pose>
		<truncated>0</truncated>
		<difficult>0</difficult>
		<occluded>0</occluded>
		<bndbox>
			<xmin>438</xmin>
			<xmax>470</xmax>
			<ymin>331</ymin>
			<ymax>364</ymax>
		</bndbox>
	</object>
	<object>
		<name>n</name>
		<pose>Unspecified</pose>
		<truncated>0</truncated>
		<difficult>0</difficult>
		<occluded>0</occluded>
		<bndbox>
			<xmin>384</xmin>
			<xmax>417</xmax>
			<ymin>368</ymin>
			<ymax>401</ymax>
		</bndbox>
	</object>
	<object>
		<name>altgr-right</name>
		<pose>Unspecified</pose>
		<truncated>0</truncated>
		<difficult>0</difficult>
		<occluded>0</occluded>
		<bndbox>
			<xmin>561</xmin>
			<xmax>609</xmax>
			<ymin>1</ymin>
			<ymax>19</ymax>
		</bndbox>
	</object>
	<object>
		<name>altgr-right</name>
		<pose>Unspecified</pose>
		<truncated>0</truncated>
		<difficult>0</difficult>
		<occluded>0</occluded>
		<bndbox>
			<xmin>483</xmin>
			<xmax>526</xmax>
			<ymin>402</ymin>
			<ymax>436</ymax>
		</bndbox>
	</object>
	<object>
		<name>z</name>
		<pose>Unspecified</pose>
		<truncated>0</truncated>
		<difficult>0</difficult>
		<occluded>0</occluded>
		<bndbox>
			<xmin>356</xmin>
			<xmax>388</xmax>
			<ymin>296</ymin>
			<ymax>329</ymax>
		</bndbox>
	</object>
	<object>
		<name>s</name>
		<pose>Unspecified</pose>
		<truncated>0</truncated>
		<difficult>0</difficult>
		<occluded>0</occluded>
		<bndbox>
			<xmin>217</xmin>
			<xmax>251</xmax>
			<ymin>336</ymin>
			<ymax>368</ymax>
		</bndbox>
	</object>
	<object>
		<name>i</name>
		<pose>Unspecified</pose>
		<truncated>0</truncated>
		<difficult>0</difficult>
		<occluded>0</occluded>
		<bndbox>
			<xmin>429</xmin>
			<xmax>460</xmax>
			<ymin>295</ymin>
			<ymax>327</ymax>
		</bndbox>
	</object>
	<object>
		<name>alt-left</name>
		<pose>Unspecified</pose>
		<truncated>0</truncated>
		<difficult>0</difficult>
		<occluded>0</occluded>
		<bndbox>
			<xmin>210</xmin>
			<xmax>254</xmax>
			<ymin>408</ymin>
			<ymax>443</ymax>
		</bndbox>
	</object>
	<object>
		<name>strg-right</name>
		<pose>Unspecified</pose>
		<truncated>0</truncated>
		<difficult>0</difficult>
		<occluded>0</occluded>
		<bndbox>
			<xmin>690</xmin>
			<xmax>738</xmax>
			<ymin>1</ymin>
			<ymax>16</ymax>
		</bndbox>
	</object>
	<object>
		<name>r</name>
		<pose>Unspecified</pose>
		<truncated>0</truncated>
		<difficult>0</difficult>
		<occluded>0</occluded>
		<bndbox>
			<xmin>282</xmin>
			<xmax>316</xmax>
			<ymin>297</ymin>
			<ymax>331</ymax>
		</bndbox>
	</object>
	<object>
		<name>strg-left</name>
		<pose>Unspecified</pose>
		<truncated>0</truncated>
		<difficult>0</difficult>
		<occluded>0</occluded>
		<bndbox>
			<xmin>111</xmin>
			<xmax>160</xmax>
			<ymin>411</ymin>
			<ymax>446</ymax>
		</bndbox>
	</object>
	<object>
		<name>w</name>
		<pose>Unspecified</pose>
		<truncated>0</truncated>
		<difficult>0</difficult>
		<occluded>0</occluded>
		<bndbox>
			<xmin>208</xmin>
			<xmax>242</xmax>
			<ymin>298</ymin>
			<ymax>332</ymax>
		</bndbox>
	</object>
	<object>
		<name>accent</name>
		<pose>Unspecified</pose>
		<truncated>0</truncated>
		<difficult>0</difficult>
		<occluded>0</occluded>
		<bndbox>
			<xmin>555</xmin>
			<xmax>587</xmax>
			<ymin>256</ymin>
			<ymax>288</ymax>
		</bndbox>
	</object>
	<object>
		<name>g</name>
		<pose>Unspecified</pose>
		<truncated>0</truncated>
		<difficult>0</difficult>
		<occluded>0</occluded>
		<bndbox>
			<xmin>328</xmin>
			<xmax>361</xmax>
			<ymin>333</ymin>
			<ymax>366</ymax>
		</bndbox>
	</object>
	<object>
		<name>u</name>
		<pose>Unspecified</pose>
		<truncated>0</truncated>
		<difficult>0</difficult>
		<occluded>0</occluded>
		<bndbox>
			<xmin>392</xmin>
			<xmax>425</xmax>
			<ymin>295</ymin>
			<ymax>328</ymax>
		</bndbox>
	</object>
	<object>
		<name>space</name>
		<pose>Unspecified</pose>
		<truncated>0</truncated>
		<difficult>0</difficult>
		<occluded>0</occluded>
		<bndbox>
			<xmin>337</xmin>
			<xmax>553</xmax>
			<ymin>1</ymin>
			<ymax>20</ymax>
		</bndbox>
	</object>
	<object>
		<name>shift-right</name>
		<pose>Unspecified</pose>
		<truncated>0</truncated>
		<difficult>0</difficult>
		<occluded>0</occluded>
		<bndbox>
			<xmin>566</xmin>
			<xmax>664</xmax>
			<ymin>363</ymin>
			<ymax>396</ymax>
		</bndbox>
	</object>
	<object>
		<name>3</name>
		<pose>Unspecified</pose>
		<truncated>0</truncated>
		<difficult>0</difficult>
		<occluded>0</occluded>
		<bndbox>
			<xmin>227</xmin>
			<xmax>260</xmax>
			<ymin>262</ymin>
			<ymax>295</ymax>
		</bndbox>
	</object>
	<object>
		<name>del</name>
		<pose>Unspecified</pose>
		<truncated>0</truncated>
		<difficult>0</difficult>
		<occluded>0</occluded>
		<bndbox>
			<xmin>591</xmin>
			<xmax>660</xmax>
			<ymin>254</ymin>
			<ymax>288</ymax>
		</bndbox>
	</object>
	<object>
		<name>l</name>
		<pose>Unspecified</pose>
		<truncated>0</truncated>
		<difficult>0</difficult>
		<occluded>0</occluded>
		<bndbox>
			<xmin>475</xmin>
			<xmax>506</xmax>
			<ymin>330</ymin>
			<ymax>363</ymax>
		</bndbox>
	</object>
	<object>
		<name>c</name>
		<pose>Unspecified</pose>
		<truncated>0</truncated>
		<difficult>0</difficult>
		<occluded>0</occluded>
		<bndbox>
			<xmin>274</xmin>
			<xmax>307</xmax>
			<ymin>370</ymin>
			<ymax>404</ymax>
		</bndbox>
	</object>
	<object>
		<name>0</name>
		<pose>Unspecified</pose>
		<truncated>0</truncated>
		<difficult>0</difficult>
		<occluded>0</occluded>
		<bndbox>
			<xmin>483</xmin>
			<xmax>515</xmax>
			<ymin>257</ymin>
			<ymax>291</ymax>
		</bndbox>
	</object>
	<object>
		<name>point</name>
		<pose>Unspecified</pose>
		<truncated>0</truncated>
		<difficult>0</difficult>
		<occluded>0</occluded>
		<bndbox>
			<xmin>494</xmin>
			<xmax>526</xmax>
			<ymin>366</ymin>
			<ymax>398</ymax>
		</bndbox>
	</object>
	<object>
		<name>t</name>
		<pose>Unspecified</pose>
		<truncated>0</truncated>
		<difficult>0</difficult>
		<occluded>0</occluded>
		<bndbox>
			<xmin>319</xmin>
			<xmax>351</xmax>
			<ymin>296</ymin>
			<ymax>329</ymax>
		</bndbox>
	</object>
	<object>
		<name>6</name>
		<pose>Unspecified</pose>
		<truncated>0</truncated>
		<difficult>0</difficult>
		<occluded>0</occluded>
		<bndbox>
			<xmin>337</xmin>
			<xmax>370</xmax>
			<ymin>261</ymin>
			<ymax>294</ymax>
		</bndbox>
	</object>
	<object>
		<name>q</name>
		<pose>Unspecified</pose>
		<truncated>0</truncated>
		<difficult>0</difficult>
		<occluded>0</occluded>
		<bndbox>
			<xmin>170</xmin>
			<xmax>204</xmax>
			<ymin>300</ymin>
			<ymax>333</ymax>
		</bndbox>
	</object>
	<object>
		<name>plus</name>
		<pose>Unspecified</pose>
		<truncated>0</truncated>
		<difficult>0</difficult>
		<occluded>0</occluded>
		<bndbox>
			<xmin>573</xmin>
			<xmax>606</xmax>
			<ymin>291</ymin>
			<ymax>325</ymax>
		</bndbox>
	</object>
	<object>
		<name>ae</name>
		<pose>Unspecified</pose>
		<truncated>0</truncated>
		<difficult>0</difficult>
		<occluded>0</occluded>
		<bndbox>
			<xmin>547</xmin>
			<xmax>580</xmax>
			<ymin>328</ymin>
			<ymax>362</ymax>
		</bndbox>
	</object>
	<object>
		<name>hash</name>
		<pose>Unspecified</pose>
		<truncated>0</truncated>
		<difficult>0</difficult>
		<occluded>0</occluded>
		<bndbox>
			<xmin>584</xmin>
			<xmax>616</xmax>
			<ymin>328</ymin>
			<ymax>360</ymax>
		</bndbox>
	</object>
	<object>
		<name>strg-right</name>
		<pose>Unspecified</pose>
		<truncated>0</truncated>
		<difficult>0</difficult>
		<occluded>0</occluded>
		<bndbox>
			<xmin>622</xmin>
			<xmax>667</xmax>
			<ymin>400</ymin>
			<ymax>434</ymax>
		</bndbox>
	</object>
	<object>
		<name>h</name>
		<pose>Unspecified</pose>
		<truncated>0</truncated>
		<difficult>0</difficult>
		<occluded>0</occluded>
		<bndbox>
			<xmin>365</xmin>
			<xmax>397</xmax>
			<ymin>332</ymin>
			<ymax>365</ymax>
		</bndbox>
	</object>
	<object>
		<name>shift-left</name>
		<pose>Unspecified</pose>
		<truncated>0</truncated>
		<difficult>0</difficult>
		<occluded>0</occluded>
		<bndbox>
			<xmin>115</xmin>
			<xmax>156</xmax>
			<ymin>375</ymin>
			<ymax>406</ymax>
		</bndbox>
	</object>
	<object>
		<name>e</name>
		<pose>Unspecified</pose>
		<truncated>0</truncated>
		<difficult>0</difficult>
		<occluded>0</occluded>
		<bndbox>
			<xmin>246</xmin>
			<xmax>278</xmax>
			<ymin>298</ymin>
			<ymax>332</ymax>
		</bndbox>
	</object>
	<object>
		<name>m</name>
		<pose>Unspecified</pose>
		<truncated>0</truncated>
		<difficult>0</difficult>
		<occluded>0</occluded>
		<bndbox>
			<xmin>420</xmin>
			<xmax>453</xmax>
			<ymin>367</ymin>
			<ymax>401</ymax>
		</bndbox>
	</object>
	<object>
		<name>tab</name>
		<pose>Unspecified</pose>
		<truncated>0</truncated>
		<difficult>0</difficult>
		<occluded>0</occluded>
		<bndbox>
			<xmin>117</xmin>
			<xmax>167</xmax>
			<ymin>301</ymin>
			<ymax>333</ymax>
		</bndbox>
	</object>
	<object>
		<name>y</name>
		<pose>Unspecified</pose>
		<truncated>0</truncated>
		<difficult>0</difficult>
		<occluded>0</occluded>
		<bndbox>
			<xmin>199</xmin>
			<xmax>232</xmax>
			<ymin>372</ymin>
			<ymax>405</ymax>
		</bndbox>
	</object>
	<object>
		<name>5</name>
		<pose>Unspecified</pose>
		<truncated>0</truncated>
		<difficult>0</difficult>
		<occluded>0</occluded>
		<bndbox>
			<xmin>300</xmin>
			<xmax>333</xmax>
			<ymin>261</ymin>
			<ymax>294</ymax>
		</bndbox>
	</object>
	<object>
		<name>comma</name>
		<pose>Unspecified</pose>
		<truncated>0</truncated>
		<difficult>0</difficult>
		<occluded>0</occluded>
		<bndbox>
			<xmin>458</xmin>
			<xmax>490</xmax>
			<ymin>367</ymin>
			<ymax>399</ymax>
		</bndbox>
	</object>
	<object>
		<name>keyboard</name>
		<pose>Unspecified</pose>
		<truncated>0</truncated>
		<difficult>0</difficult>
		<occluded>0</occluded>
		<bndbox>
			<xmin>129</xmin>
			<xmax>955</xmax>
			<ymin>1</ymin>
			<ymax>49</ymax>
		</bndbox>
	</object>
	<object>
		<name>d</name>
		<pose>Unspecified</pose>
		<truncated>0</truncated>
		<difficult>0</difficult>
		<occluded>0</occluded>
		<bndbox>
			<xmin>255</xmin>
			<xmax>287</xmax>
			<ymin>335</ymin>
			<ymax>368</ymax>
		</bndbox>
	</object>
	<object>
		<name>ue</name>
		<pose>Unspecified</pose>
		<truncated>0</truncated>
		<difficult>0</difficult>
		<occluded>0</occluded>
		<bndbox>
			<xmin>537</xmin>
			<xmax>570</xmax>
			<ymin>292</ymin>
			<ymax>326</ymax>
		</bndbox>
	</object>
	<object>
		<name>a</name>
		<pose>Unspecified</pose>
		<truncated>0</truncated>
		<difficult>0</difficult>
		<occluded>0</occluded>
		<bndbox>
			<xmin>180</xmin>
			<xmax>214</xmax>
			<ymin>336</ymin>
			<ymax>370</ymax>
		</bndbox>
	</object>
	<object>
		<name>oe</name>
		<pose>Unspecified</pose>
		<truncated>0</truncated>
		<difficult>0</difficult>
		<occluded>0</occluded>
		<bndbox>
			<xmin>511</xmin>
			<xmax>544</xmax>
			<ymin>330</ymin>
			<ymax>363</ymax>
		</bndbox>
	</object>
	<object>
		<name>2</name>
		<pose>Unspecified</pose>
		<truncated>0</truncated>
		<difficult>0</difficult>
		<occluded>0</occluded>
		<bndbox>
			<xmin>191</xmin>
			<xmax>223</xmax>
			<ymin>264</ymin>
			<ymax>296</ymax>
		</bndbox>
	</object>
	<object>
		<name>9</name>
		<pose>Unspecified</pose>
		<truncated>0</truncated>
		<difficult>0</difficult>
		<occluded>0</occluded>
		<bndbox>
			<xmin>446</xmin>
			<xmax>479</xmax>
			<ymin>259</ymin>
			<ymax>291</ymax>
		</bndbox>
	</object>
	<object>
		<name>4</name>
		<pose>Unspecified</pose>
		<truncated>0</truncated>
		<difficult>0</difficult>
		<occluded>0</occluded>
		<bndbox>
			<xmin>264</xmin>
			<xmax>296</xmax>
			<ymin>262</ymin>
			<ymax>294</ymax>
		</bndbox>
	</object>
	<object>
		<name>b</name>
		<pose>Unspecified</pose>
		<truncated>0</truncated>
		<difficult>0</difficult>
		<occluded>0</occluded>
		<bndbox>
			<xmin>347</xmin>
			<xmax>380</xmax>
			<ymin>369</ymin>
			<ymax>402</ymax>
		</bndbox>
	</object>
	<object>
		<name>ss</name>
		<pose>Unspecified</pose>
		<truncated>0</truncated>
		<difficult>0</difficult>
		<occluded>0</occluded>
		<bndbox>
			<xmin>519</xmin>
			<xmax>551</xmax>
			<ymin>257</ymin>
			<ymax>290</ymax>
		</bndbox>
	</object>
	<object>
		<name>alt-left</name>
		<pose>Unspecified</pose>
		<truncated>0</truncated>
		<difficult>0</difficult>
		<occluded>0</occluded>
		<bndbox>
			<xmin>283</xmin>
			<xmax>331</xmax>
			<ymin>1</ymin>
			<ymax>21</ymax>
		</bndbox>
	</object>
	<object>
		<name>less</name>
		<pose>Unspecified</pose>
		<truncated>0</truncated>
		<difficult>0</difficult>
		<occluded>0</occluded>
		<bndbox>
			<xmin>160</xmin>
			<xmax>196</xmax>
			<ymin>373</ymin>
			<ymax>406</ymax>
		</bndbox>
	</object>
	<object>
		<name>caret</name>
		<pose>Unspecified</pose>
		<truncated>0</truncated>
		<difficult>0</difficult>
		<occluded>0</occluded>
		<bndbox>
			<xmin>117</xmin>
			<xmax>148</xmax>
			<ymin>265</ymin>
			<ymax>298</ymax>
		</bndbox>
	</object>
	<object>
		<name>minus</name>
		<pose>Unspecified</pose>
		<truncated>0</truncated>
		<difficult>0</difficult>
		<occluded>0</occluded>
		<bndbox>
			<xmin>530</xmin>
			<xmax>562</xmax>
			<ymin>365</ymin>
			<ymax>398</ymax>
		</bndbox>
	</object>
	<object>
		<name>v</name>
		<pose>Unspecified</pose>
		<truncated>0</truncated>
		<difficult>0</difficult>
		<occluded>0</occluded>
		<bndbox>
			<xmin>310</xmin>
			<xmax>343</xmax>
			<ymin>369</ymin>
			<ymax>403</ymax>
		</bndbox>
	</object>
	<object>
		<name>j</name>
		<pose>Unspecified</pose>
		<truncated>0</truncated>
		<difficult>0</difficult>
		<occluded>0</occluded>
		<bndbox>
			<xmin>402</xmin>
			<xmax>434</xmax>
			<ymin>331</ymin>
			<ymax>364</ymax>
		</bndbox>
	</object>
	<object>
		<name>p</name>
		<pose>Unspecified</pose>
		<truncated>0</truncated>
		<difficult>0</difficult>
		<occluded>0</occluded>
		<bndbox>
			<xmin>501</xmin>
			<xmax>533</xmax>
			<ymin>293</ymin>
			<ymax>326</ymax>
		</bndbox>
	</object>
	<object>
		<name>strg-left</name>
		<pose>Unspecified</pose>
		<truncated>0</truncated>
		<difficult>0</difficult>
		<occluded>0</occluded>
		<bndbox>
			<xmin>192</xmin>
			<xmax>240</xmax>
			<ymin>1</ymin>
			<ymax>21</ymax>
		</bndbox>
	</object>
	<object>
		<name>f</name>
		<pose>Unspecified</pose>
		<truncated>0</truncated>
		<difficult>0</difficult>
		<occluded>0</occluded>
		<bndbox>
			<xmin>292</xmin>
			<xmax>324</xmax>
			<ymin>334</ymin>
			<ymax>366</ymax>
		</bndbox>
	</object>
	<object>
		<name>space</name>
		<pose>Unspecified</pose>
		<truncated>0</truncated>
		<difficult>0</difficult>
		<occluded>0</occluded>
		<bndbox>
			<xmin>256</xmin>
			<xmax>480</xmax>
			<ymin>405</ymin>
			<ymax>441</ymax>
		</bndbox>
	</object>
	<object>
		<name>shift-lock</name>
		<pose>Unspecified</pose>
		<truncated>0</truncated>
		<difficult>0</difficult>
		<occluded>0</occluded>
		<bndbox>
			<xmin>117</xmin>
			<xmax>177</xmax>
			<ymin>338</ymin>
			<ymax>371</ymax>
		</bndbox>
	</object>
	<object>
		<name>8</name>
		<pose>Unspecified</pose>
		<truncated>0</truncated>
		<difficult>0</difficult>
		<occluded>0</occluded>
		<bndbox>
			<xmin>410</xmin>
			<xmax>442</xmax>
			<ymin>259</ymin>
			<ymax>292</ymax>
		</bndbox>
	</object>
	<object>
		<name>1</name>
		<pose>Unspecified</pose>
		<truncated>0</truncated>
		<difficult>0</difficult>
		<occluded>0</occluded>
		<bndbox>
			<xmin>154</xmin>
			<xmax>186</xmax>
			<ymin>264</ymin>
			<ymax>297</ymax>
		</bndbox>
	</object>
	<object>
		<name>o</name>
		<pose>Unspecified</pose>
		<truncated>0</truncated>
		<difficult>0</difficult>
		<occluded>0</occluded>
		<bndbox>
			<xmin>465</xmin>
			<xmax>497</xmax>
			<ymin>294</ymin>
			<ymax>327</ymax>
		</bndbox>
	</object>
</annotation>
