<annotation>
	<folder></folder>
	<filename>mediarange17_jpg.rf.80310c064c251a6c7e10a81cd1537dcb.jpg</filename>
	<path>mediarange17_jpg.rf.80310c064c251a6c7e10a81cd1537dcb.jpg</path>
	<source>
		<database>roboflow.ai</database>
	</source>
	<size>
		<width>1384</width>
		<height>1038</height>
		<depth>3</depth>
	</size>
	<segmented>0</segmented>
	<object>
		<name>v</name>
		<pose>Unspecified</pose>
		<truncated>0</truncated>
		<difficult>0</difficult>
		<occluded>0</occluded>
		<bndbox>
			<xmin>362</xmin>
			<xmax>409</xmax>
			<ymin>580</ymin>
			<ymax>637</ymax>
		</bndbox>
	</object>
	<object>
		<name>shift-right</name>
		<pose>Unspecified</pose>
		<truncated>0</truncated>
		<difficult>0</difficult>
		<occluded>0</occluded>
		<bndbox>
			<xmin>836</xmin>
			<xmax>1004</xmax>
			<ymin>581</ymin>
			<ymax>639</ymax>
		</bndbox>
	</object>
	<object>
		<name>comma</name>
		<pose>Unspecified</pose>
		<truncated>0</truncated>
		<difficult>0</difficult>
		<occluded>0</occluded>
		<bndbox>
			<xmin>631</xmin>
			<xmax>678</xmax>
			<ymin>581</ymin>
			<ymax>639</ymax>
		</bndbox>
	</object>
	<object>
		<name>ue</name>
		<pose>Unspecified</pose>
		<truncated>0</truncated>
		<difficult>0</difficult>
		<occluded>0</occluded>
		<bndbox>
			<xmin>781</xmin>
			<xmax>829</xmax>
			<ymin>443</ymin>
			<ymax>502</ymax>
		</bndbox>
	</object>
	<object>
		<name>9</name>
		<pose>Unspecified</pose>
		<truncated>0</truncated>
		<difficult>0</difficult>
		<occluded>0</occluded>
		<bndbox>
			<xmin>611</xmin>
			<xmax>660</xmax>
			<ymin>375</ymin>
			<ymax>436</ymax>
		</bndbox>
	</object>
	<object>
		<name>b</name>
		<pose>Unspecified</pose>
		<truncated>0</truncated>
		<difficult>0</difficult>
		<occluded>0</occluded>
		<bndbox>
			<xmin>428</xmin>
			<xmax>477</xmax>
			<ymin>580</ymin>
			<ymax>638</ymax>
		</bndbox>
	</object>
	<object>
		<name>4</name>
		<pose>Unspecified</pose>
		<truncated>0</truncated>
		<difficult>0</difficult>
		<occluded>0</occluded>
		<bndbox>
			<xmin>275</xmin>
			<xmax>322</xmax>
			<ymin>376</ymin>
			<ymax>434</ymax>
		</bndbox>
	</object>
	<object>
		<name>3</name>
		<pose>Unspecified</pose>
		<truncated>0</truncated>
		<difficult>0</difficult>
		<occluded>0</occluded>
		<bndbox>
			<xmin>206</xmin>
			<xmax>256</xmax>
			<ymin>376</ymin>
			<ymax>435</ymax>
		</bndbox>
	</object>
	<object>
		<name>x</name>
		<pose>Unspecified</pose>
		<truncated>0</truncated>
		<difficult>0</difficult>
		<occluded>0</occluded>
		<bndbox>
			<xmin>227</xmin>
			<xmax>273</xmax>
			<ymin>581</ymin>
			<ymax>638</ymax>
		</bndbox>
	</object>
	<object>
		<name>6</name>
		<pose>Unspecified</pose>
		<truncated>0</truncated>
		<difficult>0</difficult>
		<occluded>0</occluded>
		<bndbox>
			<xmin>410</xmin>
			<xmax>459</xmax>
			<ymin>375</ymin>
			<ymax>435</ymax>
		</bndbox>
	</object>
	<object>
		<name>m</name>
		<pose>Unspecified</pose>
		<truncated>0</truncated>
		<difficult>0</difficult>
		<occluded>0</occluded>
		<bndbox>
			<xmin>563</xmin>
			<xmax>611</xmax>
			<ymin>580</ymin>
			<ymax>639</ymax>
		</bndbox>
	</object>
	<object>
		<name>1</name>
		<pose>Unspecified</pose>
		<truncated>0</truncated>
		<difficult>0</difficult>
		<occluded>0</occluded>
		<bndbox>
			<xmin>73</xmin>
			<xmax>121</xmax>
			<ymin>377</ymin>
			<ymax>435</ymax>
		</bndbox>
	</object>
	<object>
		<name>8</name>
		<pose>Unspecified</pose>
		<truncated>0</truncated>
		<difficult>0</difficult>
		<occluded>0</occluded>
		<bndbox>
			<xmin>545</xmin>
			<xmax>593</xmax>
			<ymin>376</ymin>
			<ymax>436</ymax>
		</bndbox>
	</object>
	<object>
		<name>del</name>
		<pose>Unspecified</pose>
		<truncated>0</truncated>
		<difficult>0</difficult>
		<occluded>0</occluded>
		<bndbox>
			<xmin>882</xmin>
			<xmax>1001</xmax>
			<ymin>375</ymin>
			<ymax>435</ymax>
		</bndbox>
	</object>
	<object>
		<name>f</name>
		<pose>Unspecified</pose>
		<truncated>0</truncated>
		<difficult>0</difficult>
		<occluded>0</occluded>
		<bndbox>
			<xmin>327</xmin>
			<xmax>374</xmax>
			<ymin>513</ymin>
			<ymax>569</ymax>
		</bndbox>
	</object>
	<object>
		<name>minus</name>
		<pose>Unspecified</pose>
		<truncated>0</truncated>
		<difficult>0</difficult>
		<occluded>0</occluded>
		<bndbox>
			<xmin>766</xmin>
			<xmax>814</xmax>
			<ymin>581</ymin>
			<ymax>638</ymax>
		</bndbox>
	</object>
	<object>
		<name>i</name>
		<pose>Unspecified</pose>
		<truncated>0</truncated>
		<difficult>0</difficult>
		<occluded>0</occluded>
		<bndbox>
			<xmin>580</xmin>
			<xmax>627</xmax>
			<ymin>444</ymin>
			<ymax>501</ymax>
		</bndbox>
	</object>
	<object>
		<name>e</name>
		<pose>Unspecified</pose>
		<truncated>0</truncated>
		<difficult>0</difficult>
		<occluded>0</occluded>
		<bndbox>
			<xmin>241</xmin>
			<xmax>289</xmax>
			<ymin>445</ymin>
			<ymax>502</ymax>
		</bndbox>
	</object>
	<object>
		<name>z</name>
		<pose>Unspecified</pose>
		<truncated>0</truncated>
		<difficult>0</difficult>
		<occluded>0</occluded>
		<bndbox>
			<xmin>445</xmin>
			<xmax>492</xmax>
			<ymin>444</ymin>
			<ymax>502</ymax>
		</bndbox>
	</object>
	<object>
		<name>ae</name>
		<pose>Unspecified</pose>
		<truncated>0</truncated>
		<difficult>0</difficult>
		<occluded>0</occluded>
		<bndbox>
			<xmin>799</xmin>
			<xmax>847</xmax>
			<ymin>511</ymin>
			<ymax>570</ymax>
		</bndbox>
	</object>
	<object>
		<name>p</name>
		<pose>Unspecified</pose>
		<truncated>0</truncated>
		<difficult>0</difficult>
		<occluded>0</occluded>
		<bndbox>
			<xmin>713</xmin>
			<xmax>761</xmax>
			<ymin>443</ymin>
			<ymax>501</ymax>
		</bndbox>
	</object>
	<object>
		<name>alt-left</name>
		<pose>Unspecified</pose>
		<truncated>0</truncated>
		<difficult>0</difficult>
		<occluded>0</occluded>
		<bndbox>
			<xmin>176</xmin>
			<xmax>242</xmax>
			<ymin>650</ymin>
			<ymax>706</ymax>
		</bndbox>
	</object>
	<object>
		<name>enter</name>
		<pose>Unspecified</pose>
		<truncated>0</truncated>
		<difficult>0</difficult>
		<occluded>0</occluded>
		<bndbox>
			<xmin>920</xmin>
			<xmax>1003</xmax>
			<ymin>443</ymin>
			<ymax>572</ymax>
		</bndbox>
	</object>
	<object>
		<name>caret</name>
		<pose>Unspecified</pose>
		<truncated>0</truncated>
		<difficult>0</difficult>
		<occluded>0</occluded>
		<bndbox>
			<xmin>3</xmin>
			<xmax>54</xmax>
			<ymin>376</ymin>
			<ymax>436</ymax>
		</bndbox>
	</object>
	<object>
		<name>r</name>
		<pose>Unspecified</pose>
		<truncated>0</truncated>
		<difficult>0</difficult>
		<occluded>0</occluded>
		<bndbox>
			<xmin>308</xmin>
			<xmax>356</xmax>
			<ymin>445</ymin>
			<ymax>502</ymax>
		</bndbox>
	</object>
	<object>
		<name>point</name>
		<pose>Unspecified</pose>
		<truncated>0</truncated>
		<difficult>0</difficult>
		<occluded>0</occluded>
		<bndbox>
			<xmin>699</xmin>
			<xmax>747</xmax>
			<ymin>581</ymin>
			<ymax>638</ymax>
		</bndbox>
	</object>
	<object>
		<name>oe</name>
		<pose>Unspecified</pose>
		<truncated>0</truncated>
		<difficult>0</difficult>
		<occluded>0</occluded>
		<bndbox>
			<xmin>731</xmin>
			<xmax>780</xmax>
			<ymin>512</ymin>
			<ymax>570</ymax>
		</bndbox>
	</object>
	<object>
		<name>accent</name>
		<pose>Unspecified</pose>
		<truncated>0</truncated>
		<difficult>0</difficult>
		<occluded>0</occluded>
		<bndbox>
			<xmin>814</xmin>
			<xmax>863</xmax>
			<ymin>375</ymin>
			<ymax>434</ymax>
		</bndbox>
	</object>
	<object>
		<name>n</name>
		<pose>Unspecified</pose>
		<truncated>0</truncated>
		<difficult>0</difficult>
		<occluded>0</occluded>
		<bndbox>
			<xmin>496</xmin>
			<xmax>544</xmax>
			<ymin>580</ymin>
			<ymax>637</ymax>
		</bndbox>
	</object>
	<object>
		<name>j</name>
		<pose>Unspecified</pose>
		<truncated>0</truncated>
		<difficult>0</difficult>
		<occluded>0</occluded>
		<bndbox>
			<xmin>529</xmin>
			<xmax>576</xmax>
			<ymin>513</ymin>
			<ymax>570</ymax>
		</bndbox>
	</object>
	<object>
		<name>altgr-right</name>
		<pose>Unspecified</pose>
		<truncated>0</truncated>
		<difficult>0</difficult>
		<occluded>0</occluded>
		<bndbox>
			<xmin>683</xmin>
			<xmax>750</xmax>
			<ymin>648</ymin>
			<ymax>707</ymax>
		</bndbox>
	</object>
	<object>
		<name>5</name>
		<pose>Unspecified</pose>
		<truncated>0</truncated>
		<difficult>0</difficult>
		<occluded>0</occluded>
		<bndbox>
			<xmin>341</xmin>
			<xmax>391</xmax>
			<ymin>375</ymin>
			<ymax>435</ymax>
		</bndbox>
	</object>
	<object>
		<name>l</name>
		<pose>Unspecified</pose>
		<truncated>0</truncated>
		<difficult>0</difficult>
		<occluded>0</occluded>
		<bndbox>
			<xmin>664</xmin>
			<xmax>711</xmax>
			<ymin>512</ymin>
			<ymax>569</ymax>
		</bndbox>
	</object>
	<object>
		<name>s</name>
		<pose>Unspecified</pose>
		<truncated>0</truncated>
		<difficult>0</difficult>
		<occluded>0</occluded>
		<bndbox>
			<xmin>192</xmin>
			<xmax>239</xmax>
			<ymin>513</ymin>
			<ymax>571</ymax>
		</bndbox>
	</object>
	<object>
		<name>ss</name>
		<pose>Unspecified</pose>
		<truncated>0</truncated>
		<difficult>0</difficult>
		<occluded>0</occluded>
		<bndbox>
			<xmin>745</xmin>
			<xmax>795</xmax>
			<ymin>374</ymin>
			<ymax>434</ymax>
		</bndbox>
	</object>
	<object>
		<name>c</name>
		<pose>Unspecified</pose>
		<truncated>0</truncated>
		<difficult>0</difficult>
		<occluded>0</occluded>
		<bndbox>
			<xmin>293</xmin>
			<xmax>341</xmax>
			<ymin>581</ymin>
			<ymax>638</ymax>
		</bndbox>
	</object>
	<object>
		<name>shift-left</name>
		<pose>Unspecified</pose>
		<truncated>0</truncated>
		<difficult>0</difficult>
		<occluded>0</occluded>
		<bndbox>
			<xmin>7</xmin>
			<xmax>73</xmax>
			<ymin>583</ymin>
			<ymax>640</ymax>
		</bndbox>
	</object>
	<object>
		<name>g</name>
		<pose>Unspecified</pose>
		<truncated>0</truncated>
		<difficult>0</difficult>
		<occluded>0</occluded>
		<bndbox>
			<xmin>394</xmin>
			<xmax>441</xmax>
			<ymin>513</ymin>
			<ymax>569</ymax>
		</bndbox>
	</object>
	<object>
		<name>d</name>
		<pose>Unspecified</pose>
		<truncated>0</truncated>
		<difficult>0</difficult>
		<occluded>0</occluded>
		<bndbox>
			<xmin>258</xmin>
			<xmax>306</xmax>
			<ymin>513</ymin>
			<ymax>571</ymax>
		</bndbox>
	</object>
	<object>
		<name>keyboard</name>
		<pose>Unspecified</pose>
		<truncated>0</truncated>
		<difficult>0</difficult>
		<occluded>0</occluded>
		<bndbox>
			<xmin>1</xmin>
			<xmax>1385</xmax>
			<ymin>240</ymin>
			<ymax>768</ymax>
		</bndbox>
	</object>
	<object>
		<name>strg-left</name>
		<pose>Unspecified</pose>
		<truncated>0</truncated>
		<difficult>0</difficult>
		<occluded>0</occluded>
		<bndbox>
			<xmin>7</xmin>
			<xmax>76</xmax>
			<ymin>648</ymin>
			<ymax>707</ymax>
		</bndbox>
	</object>
	<object>
		<name>a</name>
		<pose>Unspecified</pose>
		<truncated>0</truncated>
		<difficult>0</difficult>
		<occluded>0</occluded>
		<bndbox>
			<xmin>125</xmin>
			<xmax>172</xmax>
			<ymin>513</ymin>
			<ymax>570</ymax>
		</bndbox>
	</object>
	<object>
		<name>hash</name>
		<pose>Unspecified</pose>
		<truncated>0</truncated>
		<difficult>0</difficult>
		<occluded>0</occluded>
		<bndbox>
			<xmin>869</xmin>
			<xmax>917</xmax>
			<ymin>512</ymin>
			<ymax>571</ymax>
		</bndbox>
	</object>
	<object>
		<name>plus</name>
		<pose>Unspecified</pose>
		<truncated>0</truncated>
		<difficult>0</difficult>
		<occluded>0</occluded>
		<bndbox>
			<xmin>849</xmin>
			<xmax>899</xmax>
			<ymin>444</ymin>
			<ymax>504</ymax>
		</bndbox>
	</object>
	<object>
		<name>0</name>
		<pose>Unspecified</pose>
		<truncated>0</truncated>
		<difficult>0</difficult>
		<occluded>0</occluded>
		<bndbox>
			<xmin>678</xmin>
			<xmax>728</xmax>
			<ymin>376</ymin>
			<ymax>435</ymax>
		</bndbox>
	</object>
	<object>
		<name>q</name>
		<pose>Unspecified</pose>
		<truncated>0</truncated>
		<difficult>0</difficult>
		<occluded>0</occluded>
		<bndbox>
			<xmin>107</xmin>
			<xmax>155</xmax>
			<ymin>446</ymin>
			<ymax>504</ymax>
		</bndbox>
	</object>
	<object>
		<name>shift-lock</name>
		<pose>Unspecified</pose>
		<truncated>0</truncated>
		<difficult>0</difficult>
		<occluded>0</occluded>
		<bndbox>
			<xmin>4</xmin>
			<xmax>106</xmax>
			<ymin>514</ymin>
			<ymax>572</ymax>
		</bndbox>
	</object>
	<object>
		<name>k</name>
		<pose>Unspecified</pose>
		<truncated>0</truncated>
		<difficult>0</difficult>
		<occluded>0</occluded>
		<bndbox>
			<xmin>597</xmin>
			<xmax>645</xmax>
			<ymin>512</ymin>
			<ymax>569</ymax>
		</bndbox>
	</object>
	<object>
		<name>w</name>
		<pose>Unspecified</pose>
		<truncated>0</truncated>
		<difficult>0</difficult>
		<occluded>0</occluded>
		<bndbox>
			<xmin>175</xmin>
			<xmax>222</xmax>
			<ymin>446</ymin>
			<ymax>505</ymax>
		</bndbox>
	</object>
	<object>
		<name>tab</name>
		<pose>Unspecified</pose>
		<truncated>0</truncated>
		<difficult>0</difficult>
		<occluded>0</occluded>
		<bndbox>
			<xmin>6</xmin>
			<xmax>88</xmax>
			<ymin>445</ymin>
			<ymax>505</ymax>
		</bndbox>
	</object>
	<object>
		<name>2</name>
		<pose>Unspecified</pose>
		<truncated>0</truncated>
		<difficult>0</difficult>
		<occluded>0</occluded>
		<bndbox>
			<xmin>139</xmin>
			<xmax>189</xmax>
			<ymin>378</ymin>
			<ymax>436</ymax>
		</bndbox>
	</object>
	<object>
		<name>u</name>
		<pose>Unspecified</pose>
		<truncated>0</truncated>
		<difficult>0</difficult>
		<occluded>0</occluded>
		<bndbox>
			<xmin>512</xmin>
			<xmax>559</xmax>
			<ymin>444</ymin>
			<ymax>502</ymax>
		</bndbox>
	</object>
	<object>
		<name>o</name>
		<pose>Unspecified</pose>
		<truncated>0</truncated>
		<difficult>0</difficult>
		<occluded>0</occluded>
		<bndbox>
			<xmin>646</xmin>
			<xmax>695</xmax>
			<ymin>443</ymin>
			<ymax>502</ymax>
		</bndbox>
	</object>
	<object>
		<name>space</name>
		<pose>Unspecified</pose>
		<truncated>0</truncated>
		<difficult>0</difficult>
		<occluded>0</occluded>
		<bndbox>
			<xmin>258</xmin>
			<xmax>666</xmax>
			<ymin>648</ymin>
			<ymax>709</ymax>
		</bndbox>
	</object>
	<object>
		<name>less</name>
		<pose>Unspecified</pose>
		<truncated>0</truncated>
		<difficult>0</difficult>
		<occluded>0</occluded>
		<bndbox>
			<xmin>91</xmin>
			<xmax>139</xmax>
			<ymin>581</ymin>
			<ymax>640</ymax>
		</bndbox>
	</object>
	<object>
		<name>h</name>
		<pose>Unspecified</pose>
		<truncated>0</truncated>
		<difficult>0</difficult>
		<occluded>0</occluded>
		<bndbox>
			<xmin>462</xmin>
			<xmax>509</xmax>
			<ymin>513</ymin>
			<ymax>569</ymax>
		</bndbox>
	</object>
	<object>
		<name>t</name>
		<pose>Unspecified</pose>
		<truncated>0</truncated>
		<difficult>0</difficult>
		<occluded>0</occluded>
		<bndbox>
			<xmin>378</xmin>
			<xmax>424</xmax>
			<ymin>445</ymin>
			<ymax>501</ymax>
		</bndbox>
	</object>
	<object>
		<name>7</name>
		<pose>Unspecified</pose>
		<truncated>0</truncated>
		<difficult>0</difficult>
		<occluded>0</occluded>
		<bndbox>
			<xmin>478</xmin>
			<xmax>525</xmax>
			<ymin>376</ymin>
			<ymax>435</ymax>
		</bndbox>
	</object>
	<object>
		<name>y</name>
		<pose>Unspecified</pose>
		<truncated>0</truncated>
		<difficult>0</difficult>
		<occluded>0</occluded>
		<bndbox>
			<xmin>160</xmin>
			<xmax>206</xmax>
			<ymin>581</ymin>
			<ymax>638</ymax>
		</bndbox>
	</object>
	<object>
		<name>strg-right</name>
		<pose>Unspecified</pose>
		<truncated>0</truncated>
		<difficult>0</difficult>
		<occluded>0</occluded>
		<bndbox>
			<xmin>937</xmin>
			<xmax>1006</xmax>
			<ymin>650</ymin>
			<ymax>708</ymax>
		</bndbox>
	</object>
</annotation>
