<annotation>
	<folder></folder>
	<filename>microsoft10_jpg.rf.247f3066e68afe4b36abae046bc9b59c.jpg</filename>
	<path>microsoft10_jpg.rf.247f3066e68afe4b36abae046bc9b59c.jpg</path>
	<source>
		<database>roboflow.ai</database>
	</source>
	<size>
		<width>935</width>
		<height>526</height>
		<depth>3</depth>
	</size>
	<segmented>0</segmented>
	<object>
		<name>oe</name>
		<pose>Unspecified</pose>
		<truncated>0</truncated>
		<difficult>0</difficult>
		<occluded>0</occluded>
		<bndbox>
			<xmin>670</xmin>
			<xmax>719</xmax>
			<ymin>119</ymin>
			<ymax>163</ymax>
		</bndbox>
	</object>
	<object>
		<name>l</name>
		<pose>Unspecified</pose>
		<truncated>0</truncated>
		<difficult>0</difficult>
		<occluded>0</occluded>
		<bndbox>
			<xmin>617</xmin>
			<xmax>665</xmax>
			<ymin>118</ymin>
			<ymax>163</ymax>
		</bndbox>
	</object>
	<object>
		<name>f</name>
		<pose>Unspecified</pose>
		<truncated>0</truncated>
		<difficult>0</difficult>
		<occluded>0</occluded>
		<bndbox>
			<xmin>349</xmin>
			<xmax>398</xmax>
			<ymin>116</ymin>
			<ymax>160</ymax>
		</bndbox>
	</object>
	<object>
		<name>caret</name>
		<pose>Unspecified</pose>
		<truncated>0</truncated>
		<difficult>0</difficult>
		<occluded>0</occluded>
		<bndbox>
			<xmin>107</xmin>
			<xmax>146</xmax>
			<ymin>21</ymin>
			<ymax>62</ymax>
		</bndbox>
	</object>
	<object>
		<name>h</name>
		<pose>Unspecified</pose>
		<truncated>0</truncated>
		<difficult>0</difficult>
		<occluded>0</occluded>
		<bndbox>
			<xmin>457</xmin>
			<xmax>505</xmax>
			<ymin>117</ymin>
			<ymax>161</ymax>
		</bndbox>
	</object>
	<object>
		<name>shift-left</name>
		<pose>Unspecified</pose>
		<truncated>0</truncated>
		<difficult>0</difficult>
		<occluded>0</occluded>
		<bndbox>
			<xmin>83</xmin>
			<xmax>144</xmax>
			<ymin>162</ymin>
			<ymax>210</ymax>
		</bndbox>
	</object>
	<object>
		<name>n</name>
		<pose>Unspecified</pose>
		<truncated>0</truncated>
		<difficult>0</difficult>
		<occluded>0</occluded>
		<bndbox>
			<xmin>487</xmin>
			<xmax>537</xmax>
			<ymin>168</ymin>
			<ymax>214</ymax>
		</bndbox>
	</object>
	<object>
		<name>9</name>
		<pose>Unspecified</pose>
		<truncated>0</truncated>
		<difficult>0</difficult>
		<occluded>0</occluded>
		<bndbox>
			<xmin>568</xmin>
			<xmax>615</xmax>
			<ymin>28</ymin>
			<ymax>70</ymax>
		</bndbox>
	</object>
	<object>
		<name>i</name>
		<pose>Unspecified</pose>
		<truncated>0</truncated>
		<difficult>0</difficult>
		<occluded>0</occluded>
		<bndbox>
			<xmin>536</xmin>
			<xmax>582</xmax>
			<ymin>71</ymin>
			<ymax>114</ymax>
		</bndbox>
	</object>
	<object>
		<name>del</name>
		<pose>Unspecified</pose>
		<truncated>0</truncated>
		<difficult>0</difficult>
		<occluded>0</occluded>
		<bndbox>
			<xmin>772</xmin>
			<xmax>840</xmax>
			<ymin>31</ymin>
			<ymax>73</ymax>
		</bndbox>
	</object>
	<object>
		<name>y</name>
		<pose>Unspecified</pose>
		<truncated>0</truncated>
		<difficult>0</difficult>
		<occluded>0</occluded>
		<bndbox>
			<xmin>205</xmin>
			<xmax>258</xmax>
			<ymin>163</ymin>
			<ymax>210</ymax>
		</bndbox>
	</object>
	<object>
		<name>4</name>
		<pose>Unspecified</pose>
		<truncated>0</truncated>
		<difficult>0</difficult>
		<occluded>0</occluded>
		<bndbox>
			<xmin>310</xmin>
			<xmax>357</xmax>
			<ymin>24</ymin>
			<ymax>65</ymax>
		</bndbox>
	</object>
	<object>
		<name>o</name>
		<pose>Unspecified</pose>
		<truncated>0</truncated>
		<difficult>0</difficult>
		<occluded>0</occluded>
		<bndbox>
			<xmin>587</xmin>
			<xmax>634</xmax>
			<ymin>72</ymin>
			<ymax>115</ymax>
		</bndbox>
	</object>
	<object>
		<name>hash</name>
		<pose>Unspecified</pose>
		<truncated>0</truncated>
		<difficult>0</difficult>
		<occluded>0</occluded>
		<bndbox>
			<xmin>775</xmin>
			<xmax>813</xmax>
			<ymin>118</ymin>
			<ymax>163</ymax>
		</bndbox>
	</object>
	<object>
		<name>ae</name>
		<pose>Unspecified</pose>
		<truncated>0</truncated>
		<difficult>0</difficult>
		<occluded>0</occluded>
		<bndbox>
			<xmin>721</xmin>
			<xmax>771</xmax>
			<ymin>119</ymin>
			<ymax>163</ymax>
		</bndbox>
	</object>
	<object>
		<name>8</name>
		<pose>Unspecified</pose>
		<truncated>0</truncated>
		<difficult>0</difficult>
		<occluded>0</occluded>
		<bndbox>
			<xmin>518</xmin>
			<xmax>563</xmax>
			<ymin>27</ymin>
			<ymax>68</ymax>
		</bndbox>
	</object>
	<object>
		<name>t</name>
		<pose>Unspecified</pose>
		<truncated>0</truncated>
		<difficult>0</difficult>
		<occluded>0</occluded>
		<bndbox>
			<xmin>378</xmin>
			<xmax>425</xmax>
			<ymin>71</ymin>
			<ymax>113</ymax>
		</bndbox>
	</object>
	<object>
		<name>g</name>
		<pose>Unspecified</pose>
		<truncated>0</truncated>
		<difficult>0</difficult>
		<occluded>0</occluded>
		<bndbox>
			<xmin>403</xmin>
			<xmax>451</xmax>
			<ymin>117</ymin>
			<ymax>161</ymax>
		</bndbox>
	</object>
	<object>
		<name>7</name>
		<pose>Unspecified</pose>
		<truncated>0</truncated>
		<difficult>0</difficult>
		<occluded>0</occluded>
		<bndbox>
			<xmin>466</xmin>
			<xmax>513</xmax>
			<ymin>26</ymin>
			<ymax>68</ymax>
		</bndbox>
	</object>
	<object>
		<name>v</name>
		<pose>Unspecified</pose>
		<truncated>0</truncated>
		<difficult>0</difficult>
		<occluded>0</occluded>
		<bndbox>
			<xmin>374</xmin>
			<xmax>425</xmax>
			<ymin>164</ymin>
			<ymax>211</ymax>
		</bndbox>
	</object>
	<object>
		<name>altgr-right</name>
		<pose>Unspecified</pose>
		<truncated>0</truncated>
		<difficult>0</difficult>
		<occluded>0</occluded>
		<bndbox>
			<xmin>651</xmin>
			<xmax>703</xmax>
			<ymin>218</ymin>
			<ymax>265</ymax>
		</bndbox>
	</object>
	<object>
		<name>shift-lock</name>
		<pose>Unspecified</pose>
		<truncated>0</truncated>
		<difficult>0</difficult>
		<occluded>0</occluded>
		<bndbox>
			<xmin>91</xmin>
			<xmax>179</xmax>
			<ymin>113</ymin>
			<ymax>159</ymax>
		</bndbox>
	</object>
	<object>
		<name>r</name>
		<pose>Unspecified</pose>
		<truncated>0</truncated>
		<difficult>0</difficult>
		<occluded>0</occluded>
		<bndbox>
			<xmin>324</xmin>
			<xmax>372</xmax>
			<ymin>69</ymin>
			<ymax>112</ymax>
		</bndbox>
	</object>
	<object>
		<name>z</name>
		<pose>Unspecified</pose>
		<truncated>0</truncated>
		<difficult>0</difficult>
		<occluded>0</occluded>
		<bndbox>
			<xmin>430</xmin>
			<xmax>478</xmax>
			<ymin>71</ymin>
			<ymax>113</ymax>
		</bndbox>
	</object>
	<object>
		<name>0</name>
		<pose>Unspecified</pose>
		<truncated>0</truncated>
		<difficult>0</difficult>
		<occluded>0</occluded>
		<bndbox>
			<xmin>620</xmin>
			<xmax>666</xmax>
			<ymin>29</ymin>
			<ymax>70</ymax>
		</bndbox>
	</object>
	<object>
		<name>less</name>
		<pose>Unspecified</pose>
		<truncated>0</truncated>
		<difficult>0</difficult>
		<occluded>0</occluded>
		<bndbox>
			<xmin>147</xmin>
			<xmax>202</xmax>
			<ymin>162</ymin>
			<ymax>210</ymax>
		</bndbox>
	</object>
	<object>
		<name>space</name>
		<pose>Unspecified</pose>
		<truncated>0</truncated>
		<difficult>0</difficult>
		<occluded>0</occluded>
		<bndbox>
			<xmin>313</xmin>
			<xmax>650</xmax>
			<ymin>216</ymin>
			<ymax>265</ymax>
		</bndbox>
	</object>
	<object>
		<name>tab</name>
		<pose>Unspecified</pose>
		<truncated>0</truncated>
		<difficult>0</difficult>
		<occluded>0</occluded>
		<bndbox>
			<xmin>99</xmin>
			<xmax>157</xmax>
			<ymin>65</ymin>
			<ymax>110</ymax>
		</bndbox>
	</object>
	<object>
		<name>6</name>
		<pose>Unspecified</pose>
		<truncated>0</truncated>
		<difficult>0</difficult>
		<occluded>0</occluded>
		<bndbox>
			<xmin>415</xmin>
			<xmax>461</xmax>
			<ymin>26</ymin>
			<ymax>67</ymax>
		</bndbox>
	</object>
	<object>
		<name>comma</name>
		<pose>Unspecified</pose>
		<truncated>0</truncated>
		<difficult>0</difficult>
		<occluded>0</occluded>
		<bndbox>
			<xmin>592</xmin>
			<xmax>643</xmax>
			<ymin>166</ymin>
			<ymax>212</ymax>
		</bndbox>
	</object>
	<object>
		<name>u</name>
		<pose>Unspecified</pose>
		<truncated>0</truncated>
		<difficult>0</difficult>
		<occluded>0</occluded>
		<bndbox>
			<xmin>483</xmin>
			<xmax>530</xmax>
			<ymin>71</ymin>
			<ymax>114</ymax>
		</bndbox>
	</object>
	<object>
		<name>w</name>
		<pose>Unspecified</pose>
		<truncated>0</truncated>
		<difficult>0</difficult>
		<occluded>0</occluded>
		<bndbox>
			<xmin>215</xmin>
			<xmax>265</xmax>
			<ymin>67</ymin>
			<ymax>110</ymax>
		</bndbox>
	</object>
	<object>
		<name>2</name>
		<pose>Unspecified</pose>
		<truncated>0</truncated>
		<difficult>0</difficult>
		<occluded>0</occluded>
		<bndbox>
			<xmin>203</xmin>
			<xmax>253</xmax>
			<ymin>21</ymin>
			<ymax>64</ymax>
		</bndbox>
	</object>
	<object>
		<name>d</name>
		<pose>Unspecified</pose>
		<truncated>0</truncated>
		<difficult>0</difficult>
		<occluded>0</occluded>
		<bndbox>
			<xmin>294</xmin>
			<xmax>343</xmax>
			<ymin>115</ymin>
			<ymax>160</ymax>
		</bndbox>
	</object>
	<object>
		<name>k</name>
		<pose>Unspecified</pose>
		<truncated>0</truncated>
		<difficult>0</difficult>
		<occluded>0</occluded>
		<bndbox>
			<xmin>564</xmin>
			<xmax>613</xmax>
			<ymin>119</ymin>
			<ymax>163</ymax>
		</bndbox>
	</object>
	<object>
		<name>ss</name>
		<pose>Unspecified</pose>
		<truncated>0</truncated>
		<difficult>0</difficult>
		<occluded>0</occluded>
		<bndbox>
			<xmin>670</xmin>
			<xmax>717</xmax>
			<ymin>29</ymin>
			<ymax>70</ymax>
		</bndbox>
	</object>
	<object>
		<name>accent</name>
		<pose>Unspecified</pose>
		<truncated>0</truncated>
		<difficult>0</difficult>
		<occluded>0</occluded>
		<bndbox>
			<xmin>722</xmin>
			<xmax>767</xmax>
			<ymin>30</ymin>
			<ymax>70</ymax>
		</bndbox>
	</object>
	<object>
		<name>alt-left</name>
		<pose>Unspecified</pose>
		<truncated>0</truncated>
		<difficult>0</difficult>
		<occluded>0</occluded>
		<bndbox>
			<xmin>258</xmin>
			<xmax>311</xmax>
			<ymin>215</ymin>
			<ymax>264</ymax>
		</bndbox>
	</object>
	<object>
		<name>ue</name>
		<pose>Unspecified</pose>
		<truncated>0</truncated>
		<difficult>0</difficult>
		<occluded>0</occluded>
		<bndbox>
			<xmin>690</xmin>
			<xmax>739</xmax>
			<ymin>73</ymin>
			<ymax>116</ymax>
		</bndbox>
	</object>
	<object>
		<name>keyboard</name>
		<pose>Unspecified</pose>
		<truncated>0</truncated>
		<difficult>0</difficult>
		<occluded>0</occluded>
		<bndbox>
			<xmin>67</xmin>
			<xmax>880</xmax>
			<ymin>3</ymin>
			<ymax>278</ymax>
		</bndbox>
	</object>
	<object>
		<name>shift-right</name>
		<pose>Unspecified</pose>
		<truncated>0</truncated>
		<difficult>0</difficult>
		<occluded>0</occluded>
		<bndbox>
			<xmin>755</xmin>
			<xmax>865</xmax>
			<ymin>167</ymin>
			<ymax>214</ymax>
		</bndbox>
	</object>
	<object>
		<name>point</name>
		<pose>Unspecified</pose>
		<truncated>0</truncated>
		<difficult>0</difficult>
		<occluded>0</occluded>
		<bndbox>
			<xmin>647</xmin>
			<xmax>697</xmax>
			<ymin>167</ymin>
			<ymax>211</ymax>
		</bndbox>
	</object>
	<object>
		<name>5</name>
		<pose>Unspecified</pose>
		<truncated>0</truncated>
		<difficult>0</difficult>
		<occluded>0</occluded>
		<bndbox>
			<xmin>362</xmin>
			<xmax>409</xmax>
			<ymin>26</ymin>
			<ymax>66</ymax>
		</bndbox>
	</object>
	<object>
		<name>e</name>
		<pose>Unspecified</pose>
		<truncated>0</truncated>
		<difficult>0</difficult>
		<occluded>0</occluded>
		<bndbox>
			<xmin>269</xmin>
			<xmax>319</xmax>
			<ymin>68</ymin>
			<ymax>111</ymax>
		</bndbox>
	</object>
	<object>
		<name>x</name>
		<pose>Unspecified</pose>
		<truncated>0</truncated>
		<difficult>0</difficult>
		<occluded>0</occluded>
		<bndbox>
			<xmin>262</xmin>
			<xmax>314</xmax>
			<ymin>163</ymin>
			<ymax>211</ymax>
		</bndbox>
	</object>
	<object>
		<name>plus</name>
		<pose>Unspecified</pose>
		<truncated>0</truncated>
		<difficult>0</difficult>
		<occluded>0</occluded>
		<bndbox>
			<xmin>741</xmin>
			<xmax>790</xmax>
			<ymin>74</ymin>
			<ymax>116</ymax>
		</bndbox>
	</object>
	<object>
		<name>a</name>
		<pose>Unspecified</pose>
		<truncated>0</truncated>
		<difficult>0</difficult>
		<occluded>0</occluded>
		<bndbox>
			<xmin>183</xmin>
			<xmax>234</xmax>
			<ymin>113</ymin>
			<ymax>159</ymax>
		</bndbox>
	</object>
	<object>
		<name>minus</name>
		<pose>Unspecified</pose>
		<truncated>0</truncated>
		<difficult>0</difficult>
		<occluded>0</occluded>
		<bndbox>
			<xmin>699</xmin>
			<xmax>751</xmax>
			<ymin>167</ymin>
			<ymax>212</ymax>
		</bndbox>
	</object>
	<object>
		<name>enter</name>
		<pose>Unspecified</pose>
		<truncated>0</truncated>
		<difficult>0</difficult>
		<occluded>0</occluded>
		<bndbox>
			<xmin>793</xmin>
			<xmax>855</xmax>
			<ymin>74</ymin>
			<ymax>163</ymax>
		</bndbox>
	</object>
	<object>
		<name>1</name>
		<pose>Unspecified</pose>
		<truncated>0</truncated>
		<difficult>0</difficult>
		<occluded>0</occluded>
		<bndbox>
			<xmin>150</xmin>
			<xmax>200</xmax>
			<ymin>21</ymin>
			<ymax>63</ymax>
		</bndbox>
	</object>
	<object>
		<name>3</name>
		<pose>Unspecified</pose>
		<truncated>0</truncated>
		<difficult>0</difficult>
		<occluded>0</occluded>
		<bndbox>
			<xmin>256</xmin>
			<xmax>305</xmax>
			<ymin>22</ymin>
			<ymax>65</ymax>
		</bndbox>
	</object>
	<object>
		<name>j</name>
		<pose>Unspecified</pose>
		<truncated>0</truncated>
		<difficult>0</difficult>
		<occluded>0</occluded>
		<bndbox>
			<xmin>511</xmin>
			<xmax>558</xmax>
			<ymin>118</ymin>
			<ymax>162</ymax>
		</bndbox>
	</object>
	<object>
		<name>strg-left</name>
		<pose>Unspecified</pose>
		<truncated>0</truncated>
		<difficult>0</difficult>
		<occluded>0</occluded>
		<bndbox>
			<xmin>74</xmin>
			<xmax>139</xmax>
			<ymin>213</ymin>
			<ymax>263</ymax>
		</bndbox>
	</object>
	<object>
		<name>q</name>
		<pose>Unspecified</pose>
		<truncated>0</truncated>
		<difficult>0</difficult>
		<occluded>0</occluded>
		<bndbox>
			<xmin>159</xmin>
			<xmax>212</xmax>
			<ymin>66</ymin>
			<ymax>110</ymax>
		</bndbox>
	</object>
	<object>
		<name>p</name>
		<pose>Unspecified</pose>
		<truncated>0</truncated>
		<difficult>0</difficult>
		<occluded>0</occluded>
		<bndbox>
			<xmin>639</xmin>
			<xmax>687</xmax>
			<ymin>72</ymin>
			<ymax>115</ymax>
		</bndbox>
	</object>
	<object>
		<name>s</name>
		<pose>Unspecified</pose>
		<truncated>0</truncated>
		<difficult>0</difficult>
		<occluded>0</occluded>
		<bndbox>
			<xmin>238</xmin>
			<xmax>288</xmax>
			<ymin>115</ymin>
			<ymax>160</ymax>
		</bndbox>
	</object>
	<object>
		<name>b</name>
		<pose>Unspecified</pose>
		<truncated>0</truncated>
		<difficult>0</difficult>
		<occluded>0</occluded>
		<bndbox>
			<xmin>429</xmin>
			<xmax>480</xmax>
			<ymin>165</ymin>
			<ymax>211</ymax>
		</bndbox>
	</object>
	<object>
		<name>c</name>
		<pose>Unspecified</pose>
		<truncated>0</truncated>
		<difficult>0</difficult>
		<occluded>0</occluded>
		<bndbox>
			<xmin>318</xmin>
			<xmax>370</xmax>
			<ymin>164</ymin>
			<ymax>211</ymax>
		</bndbox>
	</object>
	<object>
		<name>m</name>
		<pose>Unspecified</pose>
		<truncated>0</truncated>
		<difficult>0</difficult>
		<occluded>0</occluded>
		<bndbox>
			<xmin>539</xmin>
			<xmax>588</xmax>
			<ymin>166</ymin>
			<ymax>212</ymax>
		</bndbox>
	</object>
</annotation>
