<annotation>
	<folder></folder>
	<filename>msi10_jpg.rf.80be5ddea854095d6e121976800ecf4c.jpg</filename>
	<path>msi10_jpg.rf.80be5ddea854095d6e121976800ecf4c.jpg</path>
	<source>
		<database>roboflow.ai</database>
	</source>
	<size>
		<width>934</width>
		<height>526</height>
		<depth>3</depth>
	</size>
	<segmented>0</segmented>
	<object>
		<name>u</name>
		<pose>Unspecified</pose>
		<truncated>0</truncated>
		<difficult>0</difficult>
		<occluded>0</occluded>
		<bndbox>
			<xmin>1</xmin>
			<xmax>61</xmax>
			<ymin>164</ymin>
			<ymax>234</ymax>
		</bndbox>
	</object>
	<object>
		<name>del</name>
		<pose>Unspecified</pose>
		<truncated>0</truncated>
		<difficult>0</difficult>
		<occluded>0</occluded>
		<bndbox>
			<xmin>485</xmin>
			<xmax>623</xmax>
			<ymin>83</ymin>
			<ymax>154</ymax>
		</bndbox>
	</object>
	<object>
		<name>i</name>
		<pose>Unspecified</pose>
		<truncated>0</truncated>
		<difficult>0</difficult>
		<occluded>0</occluded>
		<bndbox>
			<xmin>66</xmin>
			<xmax>147</xmax>
			<ymin>165</ymin>
			<ymax>230</ymax>
		</bndbox>
	</object>
	<object>
		<name>accent</name>
		<pose>Unspecified</pose>
		<truncated>0</truncated>
		<difficult>0</difficult>
		<occluded>0</occluded>
		<bndbox>
			<xmin>400</xmin>
			<xmax>476</xmax>
			<ymin>89</ymin>
			<ymax>154</ymax>
		</bndbox>
	</object>
	<object>
		<name>9</name>
		<pose>Unspecified</pose>
		<truncated>0</truncated>
		<difficult>0</difficult>
		<occluded>0</occluded>
		<bndbox>
			<xmin>150</xmin>
			<xmax>226</xmax>
			<ymin>89</ymin>
			<ymax>154</ymax>
		</bndbox>
	</object>
	<object>
		<name>7</name>
		<pose>Unspecified</pose>
		<truncated>0</truncated>
		<difficult>0</difficult>
		<occluded>0</occluded>
		<bndbox>
			<xmin>1</xmin>
			<xmax>59</xmax>
			<ymin>91</ymin>
			<ymax>156</ymax>
		</bndbox>
	</object>
	<object>
		<name>point</name>
		<pose>Unspecified</pose>
		<truncated>0</truncated>
		<difficult>0</difficult>
		<occluded>0</occluded>
		<bndbox>
			<xmin>210</xmin>
			<xmax>296</xmax>
			<ymin>325</ymin>
			<ymax>404</ymax>
		</bndbox>
	</object>
	<object>
		<name>enter</name>
		<pose>Unspecified</pose>
		<truncated>0</truncated>
		<difficult>0</difficult>
		<occluded>0</occluded>
		<bndbox>
			<xmin>443</xmin>
			<xmax>641</xmax>
			<ymin>239</ymin>
			<ymax>313</ymax>
		</bndbox>
	</object>
	<object>
		<name>m</name>
		<pose>Unspecified</pose>
		<truncated>0</truncated>
		<difficult>0</difficult>
		<occluded>0</occluded>
		<bndbox>
			<xmin>21</xmin>
			<xmax>111</xmax>
			<ymin>327</ymin>
			<ymax>409</ymax>
		</bndbox>
	</object>
	<object>
		<name>hash</name>
		<pose>Unspecified</pose>
		<truncated>0</truncated>
		<difficult>0</difficult>
		<occluded>0</occluded>
		<bndbox>
			<xmin>503</xmin>
			<xmax>634</xmax>
			<ymin>162</ymin>
			<ymax>233</ymax>
		</bndbox>
	</object>
	<object>
		<name>0</name>
		<pose>Unspecified</pose>
		<truncated>0</truncated>
		<difficult>0</difficult>
		<occluded>0</occluded>
		<bndbox>
			<xmin>234</xmin>
			<xmax>310</xmax>
			<ymin>89</ymin>
			<ymax>154</ymax>
		</bndbox>
	</object>
	<object>
		<name>keyboard</name>
		<pose>Unspecified</pose>
		<truncated>0</truncated>
		<difficult>0</difficult>
		<occluded>0</occluded>
		<bndbox>
			<xmin>1</xmin>
			<xmax>935</xmax>
			<ymin>17</ymin>
			<ymax>524</ymax>
		</bndbox>
	</object>
	<object>
		<name>plus</name>
		<pose>Unspecified</pose>
		<truncated>0</truncated>
		<difficult>0</difficult>
		<occluded>0</occluded>
		<bndbox>
			<xmin>420</xmin>
			<xmax>496</xmax>
			<ymin>164</ymin>
			<ymax>229</ymax>
		</bndbox>
	</object>
	<object>
		<name>comma</name>
		<pose>Unspecified</pose>
		<truncated>0</truncated>
		<difficult>0</difficult>
		<occluded>0</occluded>
		<bndbox>
			<xmin>115</xmin>
			<xmax>203</xmax>
			<ymin>326</ymin>
			<ymax>405</ymax>
		</bndbox>
	</object>
	<object>
		<name>shift-right</name>
		<pose>Unspecified</pose>
		<truncated>0</truncated>
		<difficult>0</difficult>
		<occluded>0</occluded>
		<bndbox>
			<xmin>398</xmin>
			<xmax>562</xmax>
			<ymin>321</ymin>
			<ymax>399</ymax>
		</bndbox>
	</object>
	<object>
		<name>l</name>
		<pose>Unspecified</pose>
		<truncated>0</truncated>
		<difficult>0</difficult>
		<occluded>0</occluded>
		<bndbox>
			<xmin>170</xmin>
			<xmax>253</xmax>
			<ymin>240</ymin>
			<ymax>314</ymax>
		</bndbox>
	</object>
	<object>
		<name>less</name>
		<pose>Unspecified</pose>
		<truncated>0</truncated>
		<difficult>0</difficult>
		<occluded>0</occluded>
		<bndbox>
			<xmin>187</xmin>
			<xmax>278</xmax>
			<ymin>415</ymin>
			<ymax>505</ymax>
		</bndbox>
	</object>
	<object>
		<name>ae</name>
		<pose>Unspecified</pose>
		<truncated>0</truncated>
		<difficult>0</difficult>
		<occluded>0</occluded>
		<bndbox>
			<xmin>353</xmin>
			<xmax>434</xmax>
			<ymin>239</ymin>
			<ymax>311</ymax>
		</bndbox>
	</object>
	<object>
		<name>altgr-right</name>
		<pose>Unspecified</pose>
		<truncated>0</truncated>
		<difficult>0</difficult>
		<occluded>0</occluded>
		<bndbox>
			<xmin>88</xmin>
			<xmax>182</xmax>
			<ymin>416</ymin>
			<ymax>505</ymax>
		</bndbox>
	</object>
	<object>
		<name>strg-right</name>
		<pose>Unspecified</pose>
		<truncated>0</truncated>
		<difficult>0</difficult>
		<occluded>0</occluded>
		<bndbox>
			<xmin>382</xmin>
			<xmax>472</xmax>
			<ymin>412</ymin>
			<ymax>501</ymax>
		</bndbox>
	</object>
	<object>
		<name>j</name>
		<pose>Unspecified</pose>
		<truncated>0</truncated>
		<difficult>0</difficult>
		<occluded>0</occluded>
		<bndbox>
			<xmin>1</xmin>
			<xmax>75</xmax>
			<ymin>243</ymin>
			<ymax>319</ymax>
		</bndbox>
	</object>
	<object>
		<name>minus</name>
		<pose>Unspecified</pose>
		<truncated>0</truncated>
		<difficult>0</difficult>
		<occluded>0</occluded>
		<bndbox>
			<xmin>305</xmin>
			<xmax>391</xmax>
			<ymin>323</ymin>
			<ymax>402</ymax>
		</bndbox>
	</object>
	<object>
		<name>ue</name>
		<pose>Unspecified</pose>
		<truncated>0</truncated>
		<difficult>0</difficult>
		<occluded>0</occluded>
		<bndbox>
			<xmin>330</xmin>
			<xmax>406</xmax>
			<ymin>162</ymin>
			<ymax>227</ymax>
		</bndbox>
	</object>
	<object>
		<name>8</name>
		<pose>Unspecified</pose>
		<truncated>0</truncated>
		<difficult>0</difficult>
		<occluded>0</occluded>
		<bndbox>
			<xmin>66</xmin>
			<xmax>142</xmax>
			<ymin>92</ymin>
			<ymax>157</ymax>
		</bndbox>
	</object>
	<object>
		<name>oe</name>
		<pose>Unspecified</pose>
		<truncated>0</truncated>
		<difficult>0</difficult>
		<occluded>0</occluded>
		<bndbox>
			<xmin>262</xmin>
			<xmax>343</xmax>
			<ymin>239</ymin>
			<ymax>314</ymax>
		</bndbox>
	</object>
	<object>
		<name>k</name>
		<pose>Unspecified</pose>
		<truncated>0</truncated>
		<difficult>0</difficult>
		<occluded>0</occluded>
		<bndbox>
			<xmin>78</xmin>
			<xmax>163</xmax>
			<ymin>240</ymin>
			<ymax>317</ymax>
		</bndbox>
	</object>
	<object>
		<name>p</name>
		<pose>Unspecified</pose>
		<truncated>0</truncated>
		<difficult>0</difficult>
		<occluded>0</occluded>
		<bndbox>
			<xmin>242</xmin>
			<xmax>320</xmax>
			<ymin>162</ymin>
			<ymax>229</ymax>
		</bndbox>
	</object>
	<object>
		<name>ss</name>
		<pose>Unspecified</pose>
		<truncated>0</truncated>
		<difficult>0</difficult>
		<occluded>0</occluded>
		<bndbox>
			<xmin>318</xmin>
			<xmax>394</xmax>
			<ymin>90</ymin>
			<ymax>155</ymax>
		</bndbox>
	</object>
	<object>
		<name>o</name>
		<pose>Unspecified</pose>
		<truncated>0</truncated>
		<difficult>0</difficult>
		<occluded>0</occluded>
		<bndbox>
			<xmin>154</xmin>
			<xmax>235</xmax>
			<ymin>163</ymin>
			<ymax>230</ymax>
		</bndbox>
	</object>
</annotation>
